guardrails_hub_types/__init__.py
guardrails_hub_types/py.typed
guardrails_hub_types/models/__init__.py
guardrails_hub_types/models/applicator.py
guardrails_hub_types/models/content.py
guardrails_hub_types/models/contributor.py
guardrails_hub_types/models/core.py
guardrails_hub_types/models/format_annotation.py
guardrails_hub_types/models/manifest.py
guardrails_hub_types/models/manifest_parameters.py
guardrails_hub_types/models/meta_data.py
guardrails_hub_types/models/model_auth.py
guardrails_hub_types/models/model_schema.py
guardrails_hub_types/models/repository.py
guardrails_hub_types/models/simple_types.py
guardrails_hub_types/models/tags.py
guardrails_hub_types/models/unevaluated.py
guardrails_hub_types/models/validation.py
guardrails_hub_types/models/validation_type.py
guardrails_hub_types-0.0.4.dist-info/LICENSE
guardrails_hub_types-0.0.4.dist-info/METADATA
guardrails_hub_types-0.0.4.dist-info/WHEEL
guardrails_hub_types-0.0.4.dist-info/top_level.txt
guardrails_hub_types-0.0.4.dist-info/RECORD
