Metadata-Version: 2.1
Name: guardrails_hub_types
Version: 0.0.4
Summary: Guardrails Hub Types.
Author-email: Guardrails AI <contact@guardrailsai.com>
License:                                  Apache License
Keywords: Guardrails,Guardrails AI,Guardrails Hub,Guardrails Hub Types
Requires-Python: >=3.8, <4
License-File: LICENSE
Provides-Extra: dev
Requires-Dist: pyright; extra == "dev"
Requires-Dist: pytest; extra == "dev"
Requires-Dist: pytest-cov; extra == "dev"
Requires-Dist: ruff; extra == "dev"
